moudle/__init__.py
moudle/core.py
ragcheckerzhongshui-0.0.1.dist-info/LICENSE
ragcheckerzhongshui-0.0.1.dist-info/METADATA
ragcheckerzhongshui-0.0.1.dist-info/WHEEL
ragcheckerzhongshui-0.0.1.dist-info/top_level.txt
ragcheckerzhongshui-0.0.1.dist-info/RECORD
